README.md
setup.py
FlowMagic/FlowMagic.py
FlowMagic/__init__.py
FlowMagic.egg-info/PKG-INFO
FlowMagic.egg-info/SOURCES.txt
FlowMagic.egg-info/dependency_links.txt
FlowMagic.egg-info/top_level.txt