Metadata-Version: 1.0
Name: FlowMagic
Version: 0.2.6
Summary: FlowMagic SDK
Home-page: UNKNOWN
Author: Abhishek Rana
Author-email: abhishek.rana@mantralabsglobal.com
License: UNKNOWN
Platform: UNKNOWN
